datahub_airflow_plugin/__init__.py
datahub_airflow_plugin/datahub_plugin.py
treff7es_datahub_airflow_plugin-0.0.0.3.dist-info/METADATA
treff7es_datahub_airflow_plugin-0.0.0.3.dist-info/WHEEL
treff7es_datahub_airflow_plugin-0.0.0.3.dist-info/entry_points.txt
treff7es_datahub_airflow_plugin-0.0.0.3.dist-info/top_level.txt
treff7es_datahub_airflow_plugin-0.0.0.3.dist-info/RECORD
