Metadata-Version: 2.1
Name: treff7es-datahub-airflow-plugin
Version: 0.0.0.3
Summary: Datahub Airflow plugin to capture executions and send to Datahub
Home-page: https://datahubproject.io/
License: Apache License 2.0
Project-URL: Documentation, https://datahubproject.io/docs/
Project-URL: Source, https://github.com/datahub-project/datahub
Project-URL: Changelog, https://github.com/datahub-project/datahub/releases
Platform: UNKNOWN
Classifier: Development Status :: 5 - Production/Stable
Classifier: Programming Language :: Python
Classifier: Programming Language :: Python :: 3
Classifier: Programming Language :: Python :: 3 :: Only
Classifier: Programming Language :: Python :: 3.6
Classifier: Programming Language :: Python :: 3.7
Classifier: Programming Language :: Python :: 3.8
Classifier: Programming Language :: Python :: 3.9
Classifier: Intended Audience :: Developers
Classifier: Intended Audience :: Information Technology
Classifier: Intended Audience :: System Administrators
Classifier: License :: OSI Approved
Classifier: License :: OSI Approved :: Apache Software License
Classifier: Operating System :: Unix
Classifier: Operating System :: POSIX :: Linux
Classifier: Environment :: Console
Classifier: Environment :: MacOS X
Classifier: Topic :: Software Development
Requires-Python: >=3.6
Requires-Dist: apache-airflow (>=1.10.2)
Requires-Dist: mypy-extensions (>=0.4.3)
Requires-Dist: pydantic (>=1.5.1)
Requires-Dist: typing-extensions (>=3.10.0.2)
Requires-Dist: acryl-datahub[airflow]
Requires-Dist: typing-inspect
Requires-Dist: dataclasses (>=0.6) ; python_version < "3.7"
Provides-Extra: dev
Requires-Dist: types-requests ; extra == 'dev'
Requires-Dist: types-PyYAML ; extra == 'dev'
Requires-Dist: types-click (==0.1.12) ; extra == 'dev'
Requires-Dist: pytest-docker (<0.12,>=0.10.3) ; extra == 'dev'
Requires-Dist: flake8-tidy-imports (>=4.3.0) ; extra == 'dev'
Requires-Dist: pydantic (>=1.9.0) ; extra == 'dev'
Requires-Dist: types-six ; extra == 'dev'
Requires-Dist: deepdiff ; extra == 'dev'
Requires-Dist: jsonpickle ; extra == 'dev'
Requires-Dist: apache-airflow (>=1.10.2) ; extra == 'dev'
Requires-Dist: types-tabulate ; extra == 'dev'
Requires-Dist: pytest-cov (>=2.8.1) ; extra == 'dev'
Requires-Dist: mypy-extensions (>=0.4.3) ; extra == 'dev'
Requires-Dist: pydantic (>=1.5.1) ; extra == 'dev'
Requires-Dist: types-pytz ; extra == 'dev'
Requires-Dist: coverage (>=5.1) ; extra == 'dev'
Requires-Dist: tox ; extra == 'dev'
Requires-Dist: flake8 (>=3.8.3) ; extra == 'dev'
Requires-Dist: build ; extra == 'dev'
Requires-Dist: types-toml ; extra == 'dev'
Requires-Dist: types-python-dateutil ; extra == 'dev'
Requires-Dist: black (>=21.12b0) ; extra == 'dev'
Requires-Dist: types-cachetools ; extra == 'dev'
Requires-Dist: typing-inspect ; extra == 'dev'
Requires-Dist: mypy (>=0.920) ; extra == 'dev'
Requires-Dist: types-pkg-resources ; extra == 'dev'
Requires-Dist: types-dataclasses ; extra == 'dev'
Requires-Dist: packaging ; extra == 'dev'
Requires-Dist: pytest (>=6.2.2) ; extra == 'dev'
Requires-Dist: requests-mock ; extra == 'dev'
Requires-Dist: acryl-datahub[airflow] ; extra == 'dev'
Requires-Dist: types-freezegun ; extra == 'dev'
Requires-Dist: isort (>=5.7.0) ; extra == 'dev'
Requires-Dist: pytest-asyncio (>=0.16.0) ; extra == 'dev'
Requires-Dist: twine ; extra == 'dev'
Requires-Dist: typing-extensions (>=3.10.0.2) ; extra == 'dev'
Requires-Dist: freezegun ; extra == 'dev'
Requires-Dist: sqlalchemy-stubs ; extra == 'dev'
Provides-Extra: dev-airflow1
Requires-Dist: types-requests ; extra == 'dev-airflow1'
Requires-Dist: types-PyYAML ; extra == 'dev-airflow1'
Requires-Dist: types-click (==0.1.12) ; extra == 'dev-airflow1'
Requires-Dist: pytest-docker (<0.12,>=0.10.3) ; extra == 'dev-airflow1'
Requires-Dist: apache-airflow-backport-providers-snowflake ; extra == 'dev-airflow1'
Requires-Dist: flake8-tidy-imports (>=4.3.0) ; extra == 'dev-airflow1'
Requires-Dist: pydantic (>=1.9.0) ; extra == 'dev-airflow1'
Requires-Dist: types-six ; extra == 'dev-airflow1'
Requires-Dist: deepdiff ; extra == 'dev-airflow1'
Requires-Dist: jsonpickle ; extra == 'dev-airflow1'
Requires-Dist: apache-airflow (>=1.10.2) ; extra == 'dev-airflow1'
Requires-Dist: types-tabulate ; extra == 'dev-airflow1'
Requires-Dist: pytest-cov (>=2.8.1) ; extra == 'dev-airflow1'
Requires-Dist: mypy-extensions (>=0.4.3) ; extra == 'dev-airflow1'
Requires-Dist: pydantic (>=1.5.1) ; extra == 'dev-airflow1'
Requires-Dist: types-pytz ; extra == 'dev-airflow1'
Requires-Dist: apache-airflow (==1.10.15) ; extra == 'dev-airflow1'
Requires-Dist: coverage (>=5.1) ; extra == 'dev-airflow1'
Requires-Dist: tox ; extra == 'dev-airflow1'
Requires-Dist: flake8 (>=3.8.3) ; extra == 'dev-airflow1'
Requires-Dist: build ; extra == 'dev-airflow1'
Requires-Dist: types-toml ; extra == 'dev-airflow1'
Requires-Dist: types-python-dateutil ; extra == 'dev-airflow1'
Requires-Dist: black (>=21.12b0) ; extra == 'dev-airflow1'
Requires-Dist: types-cachetools ; extra == 'dev-airflow1'
Requires-Dist: typing-inspect ; extra == 'dev-airflow1'
Requires-Dist: mypy (>=0.920) ; extra == 'dev-airflow1'
Requires-Dist: types-pkg-resources ; extra == 'dev-airflow1'
Requires-Dist: types-dataclasses ; extra == 'dev-airflow1'
Requires-Dist: packaging ; extra == 'dev-airflow1'
Requires-Dist: pytest (>=6.2.2) ; extra == 'dev-airflow1'
Requires-Dist: requests-mock ; extra == 'dev-airflow1'
Requires-Dist: acryl-datahub[airflow] ; extra == 'dev-airflow1'
Requires-Dist: types-freezegun ; extra == 'dev-airflow1'
Requires-Dist: isort (>=5.7.0) ; extra == 'dev-airflow1'
Requires-Dist: pytest-asyncio (>=0.16.0) ; extra == 'dev-airflow1'
Requires-Dist: twine ; extra == 'dev-airflow1'
Requires-Dist: typing-extensions (>=3.10.0.2) ; extra == 'dev-airflow1'
Requires-Dist: freezegun ; extra == 'dev-airflow1'
Requires-Dist: sqlalchemy-stubs ; extra == 'dev-airflow1'
Provides-Extra: dev-airflow1-base
Requires-Dist: apache-airflow (==1.10.15) ; extra == 'dev-airflow1-base'
Requires-Dist: apache-airflow-backport-providers-snowflake ; extra == 'dev-airflow1-base'
Requires-Dist: dataclasses (>=0.6) ; (python_version < "3.7") and extra == 'dev-airflow1'
Requires-Dist: dataclasses (>=0.6) ; (python_version < "3.7") and extra == 'dev'
